[
    {
        "name": "Saudi Arabia",
        "name_ar": "السعودية",
        "name_en": "Saudi Arabia",
        "name_ru": "Saudiov",
        "calling_code": "966",
        "country_code": "KSA",
        "image": "11MomE3bLeYA1YIu4IoNsMMizBQ4ig9R1zn0oPGE.png",
        "order": "1",
        "has_currency": "1",
        "exchange_rate": "1.00",
        "currency_symbol_ar": "ر.س",
        "currency_symbol_en": "SR",
        "currency_symbol_ru": "SR",
        "active": "1",
        "is_local": "1",
        "minimum_shipment_charge": "3",
        "fixed_shipment_charge": "5",
        "longitude": "178.970071",
        "latitude": ",-20.982252",
        "lang": "ar",
        "created_at": "2019-07-16 09:29:14",
        "updated_at": "2019-07-17 07:30:13"
    },
    {
        "name": "Kuwait",
        "name_ar": "الكويت",
        "name_en": "kuwait",
        "name_ru": "kuwaitov",
        "calling_code": "965",
        "country_code": "KWT",
        "image": "rQwDnpZI77v3jYTDuKrHMdslQwVXEdl86WnKxN55.png",
        "order": "2",
        "has_currency": "1",
        "currency_symbol_ar": "د.ك",
        "currency_symbol_en": "KD",
        "currency_symbol_ru": "KD",
        "active": "1",
        "is_local": "0",
        "exchange_rate": "0.082",
        "minimum_shipment_charge": "2",
        "fixed_shipment_charge": "2",
        "longitude": "89.781241",
        "latitude": ",-14.328771",
        "lang": "ar",
        "created_at": "2019-07-16 09:29:14",
        "updated_at": "2019-07-18 08:09:03"
    },
    {
        "name": "Russia",
        "name_ar": "روسيا",
        "name_en": "Russia",
        "name_ru": "Russiaov",
        "calling_code": "123",
        "country_code": "RU",
        "image": "11MomE3bLeYA1YIu4IoNsMMizBQ4ig9R1zn0oPGE.png",
        "order": "3",
        "has_currency": "1",
        "exchange_rate": "25.89",
        "currency_symbol_ar": "ر.ر",
        "currency_symbol_en": "RUB",
        "currency_symbol_ru": "RUB",
        "active": "1",
        "is_local": "0",
        "minimum_shipment_charge": "3",
        "fixed_shipment_charge": "5",
        "longitude": "178.970071",
        "latitude": ",-20.982252",
        "lang": "ru",
        "created_at": "2019-07-16 09:29:14",
        "updated_at": "2019-07-17 07:30:13"
    },
    {
        "name": "USA",
        "name_ar": "الولايات المتحدة",
        "name_en": "United States",
        "name_ru": "Unitedtov Statov",
        "calling_code": "1",
        "country_code": "USA",
        "image": "YWtmJm6gScgbTK7I83Q0kDz5C5BEPWIhvYW8egSE.png",
        "order": "6",
        "has_currency": "1",
        "exchange_rate": "0.27",
        "currency_symbol_ar": "د.أ",
        "currency_symbol_en": "US",
        "currency_symbol_ru": "US",
        "active": "1",
        "is_local": "0",
        "minimum_shipment_charge": "5",
        "fixed_shipment_charge": "5",
        "longitude": "100.969916",
        "latitude": ",-16.254294",
        "lang": "en",
        "created_at": "2019-07-16 09:29:14",
        "updated_at": "2019-07-18 08:16:36"
    }
]